{
  "project_info": {
    "project_number": "595597079040",
    "project_id": "acceslink-lgbtq",
    "storage_bucket": "acceslink-lgbtq.firebasestorage.app"
  },
  "client": [
    {
      "client_info": {
        "mobilesdk_app_id": "1:595597079040:android:598b0e16a92f0fb2c49ee5",
        "android_client_info": {
          "package_name": "com.accesslinklgbtq.lgbtq"
        }
      },
      "oauth_client": [
        {
          "client_id": "595597079040-0ktcl9hs1fm8iouuru2nt468p6us8g81.apps.googleusercontent.com",
          "client_type": 1,
          "android_info": {
            "package_name": "com.accesslinklgbtq.lgbtq",
            "certificate_hash": "e40c177a294a97d04028736e69f0347e51bffd46"
          }
        }
      ],
      "api_key": [
        {
          "current_key": "AIzaSyCIOMEqs_o2VTxj7HnVqGMtG5u2qRuT6TU"
        }
      ],
      "services": {
        "appinvite_service": {
          "other_platform_oauth_client": []
        }
      }
    }
  ],
  "configuration_version": "1"
}